__init__.py
parserproxy.py
requestsgarant.py
test_parserproxy.py
test_watsapp.py
watsapp.py
requestsgarant-0.1.16.dist-info/LICENSE
requestsgarant-0.1.16.dist-info/METADATA
requestsgarant-0.1.16.dist-info/WHEEL
requestsgarant-0.1.16.dist-info/top_level.txt
requestsgarant-0.1.16.dist-info/RECORD
