Metadata-Version: 2.1
Name: requestsgarant
Version: 0.1.16
Summary: Garant success web-requests
Author-email: plp-kolyan <plp-kolyan@mail.ru>
License: Copyright (c) 2018 The Python Packaging Authority
Project-URL: Homepage, https://github.com/plp-kolyan/CustomRequests.git
Classifier: Programming Language :: Python :: 3
Classifier: License :: OSI Approved :: MIT License
Classifier: Operating System :: OS Independent
Requires-Python: >=3.7
License-File: LICENSE
